pysbark/__init__.py
pysbark/main.py
pysbark-0.21.0.dist-info/METADATA
pysbark-0.21.0.dist-info/WHEEL
pysbark-0.21.0.dist-info/top_level.txt
pysbark-0.21.0.dist-info/RECORD
