Metadata-Version: 2.1
Name: pysbark
Version: 0.21.0
Summary: Package used to run whoami
Home-page: https://github.com/TODOO
Author: Maxton Bernal
Author-email: MaxtonBernal@proton.me
License: UNKNOWN
Platform: UNKNOWN
Classifier: Programming Language :: Python :: 3
Classifier: License :: OSI Approved :: MIT License
Classifier: Operating System :: OS Independent
Requires-Python: >=3.6
